pyrogen/__init__.py
pyrogen/version.py
pyrogen/ecs3/__init__.py
pyrogen/ecs3/components/__init__.py
pyrogen/ecs3/components/component.py
pyrogen/ecs3/components/gfx.py
pyrogen/ecs3/components/input.py
pyrogen/ecs3/components/script.py
pyrogen/ecs3/gpu/__init__.py
pyrogen/ecs3/gpu/fsgpu_buffer.py
pyrogen/ecs3/gpu/fsgpu_main.py
pyrogen/ecs3/gpu/opengl_data.py
pyrogen/ecs3/loader/__init__.py
pyrogen/ecs3/loader/bin_packing.py
pyrogen/ecs3/loader/loader.py
pyrogen/ecs3/main/__init__.py
pyrogen/ecs3/main/common.py
pyrogen/ecs3/main/entity.py
pyrogen/ecs3/main/pyrogen_app.py
pyrogen/ecs3/main/scene.py
pyrogen/ecs3/main/world.py
pyrogen/ecs3/shaders/__init__.py
pyrogen/ecs3/shaders/default_shader.py
pyrogen/ecs3/shaders/simple_shader.py
pyrogen/ecs3/systems/__init__.py
pyrogen/ecs3/systems/base_system.py
pyrogen/ecs3/systems/gfx_system.py
pyrogen/ecs3/systems/input_system.py
pyrogen/ecs3/systems/scene_system.py
pyrogen/ecs3/systems/script_system.py
pyrogen/ecs3/users/__init__.py
pyrogen/ecs3/users/follow.py
pyrogen/tutorials/__init__.py
pyrogen/tutorials/dev_test/__init__.py
pyrogen/tutorials/dev_test/dev_test.py
pyrogen/tutorials/dev_test/components/__init__.py
pyrogen/tutorials/dev_test/components/scripts.py
pyrogen/tutorials/dev_test/resources/__init__.py
pyrogen/tutorials/dev_test/resources/atlas/__init__.py
pyrogen/tutorials/dev_test/resources/atlas/atlas_8d1b0a62d15ef6bd2681c81f1225d4b4.png
pyrogen/tutorials/dev_test/resources/atlas/atlas_c0ad2e13be2b3b5347280323bd89fa51.png
pyrogen/tutorials/dev_test/resources/atlas/font_mandala_64_1.png
pyrogen/tutorials/dev_test/resources/atlas/font_subway_64_1.png
pyrogen/tutorials/dev_test/resources/fonts/Mandala.ttf
pyrogen/tutorials/dev_test/resources/fonts/subway.ttf
pyrogen/tutorials/dev_test/resources/images/__init__.py
pyrogen/tutorials/dev_test/resources/images/ball.png
pyrogen/tutorials/dev_test/resources/images/characters001.png
pyrogen/tutorials/dev_test/resources/images/image001.png
pyrogen-0.4.6.dist-info/LICENSE
pyrogen-0.4.6.dist-info/METADATA
pyrogen-0.4.6.dist-info/WHEEL
pyrogen-0.4.6.dist-info/top_level.txt
pyrogen-0.4.6.dist-info/RECORD
