Metadata-Version: 2.1
Name: pyrogen
Version: 0.4.6
Summary: Entity-Component-System framework for 2D games
Home-page: https://github.com/Romuald78/pyrogen
Author: Romuald GRIGNON
Author-email: romuald.grignon@gmail.com
License: UNKNOWN
Project-URL: Bug Tracker, https://github.com/Romuald78/pyrogen/issues
Platform: UNKNOWN
Classifier: Development Status :: 1 - Planning
Classifier: License :: OSI Approved :: MIT License
Classifier: Natural Language :: English
Classifier: Topic :: Software Development :: Libraries :: Python Modules
Classifier: Intended Audience :: Developers
Classifier: Operating System :: OS Independent
Classifier: Programming Language :: Python
Classifier: Programming Language :: Python :: 3
Classifier: Programming Language :: Python :: 3.6
Classifier: Programming Language :: Python :: 3.7
Classifier: Programming Language :: Python :: 3.8
Classifier: Programming Language :: Python :: 3.9
Requires-Python: >=3.7
Requires-Dist: pyglet (==1.5.17)
Requires-Dist: pillow (==8.1.2)
Requires-Dist: moderngl (==5.6.4)
Requires-Dist: moderngl-window (==2.3.0)
